[
  {
    "IsFourWheelDrive": false,
    "TowingCapacity": 5000,
    "CargoSpace": 15,
    "EngineType": "V6",
    "MPG": 25,
    "Range": 500,
    "FuelCapacity": 20,
    "Guid": "c0d1d5be-1aa2-4a51-8a3f-9c763338d13f",
    "Color": "Silver",
    "Capacity": 4,
    "Make": "Toyota",
    "Model": "4Runner",
    "Year": 1997,
    "VehicleTypeEnum": 2,
    "CurrentMileage": 254334,
    "GasEngine": null,
    "DieselEngine": null,
    "ElectricMotor": null,
    "Engine": {
      "$type": "gas",
      "RecommendedFuelOctane": 85,
      "HasSuperCharger": false,
      "NumberOfCylinders": 6,
      "HasTurbo": false,
      "FuelType": "Gas",
      "HorsePower": 330,
      "Torque": 360
    }
  },
  {
    "IsFourWheelDrive": false,
    "TowingCapacity": 5000,
    "CargoSpace": 15,
    "EngineType": "V8",
    "MPG": 25,
    "Range": 500,
    "FuelCapacity": 20,
    "Guid": "f7027d38-43f5-4f17-9644-f2aa9f4ed8e7",
    "Color": "Red",
    "Capacity": 4,
    "Make": "Ford",
    "Model": "Explorer",
    "Year": 1998,
    "VehicleTypeEnum": 2,
    "CurrentMileage": 303657,
    "GasEngine": null,
    "DieselEngine": null,
    "ElectricMotor": null,
    "Engine": {
      "$type": "gas",
      "RecommendedFuelOctane": 85,
      "HasSuperCharger": false,
      "NumberOfCylinders": 8,
      "HasTurbo": false,
      "FuelType": "Gas",
      "HorsePower": 400,
      "Torque": 455
    }
  },
  {
    "IsFourWheelDrive": false,
    "TowingCapacity": 5000,
    "CargoSpace": 15,
    "EngineType": "V6 Hybrid",
    "MPG": 25,
    "Range": 500,
    "FuelCapacity": 20,
    "Guid": "db1cdead-a8c0-4f56-9d9d-f18409809633",
    "Color": "White",
    "Capacity": 4,
    "Make": "Chevrolet",
    "Model": "Tahoe",
    "Year": 2001,
    "VehicleTypeEnum": 2,
    "CurrentMileage": 244890,
    "GasEngine": null,
    "DieselEngine": null,
    "ElectricMotor": null,
    "Engine": {
      "$type": "gas",
      "RecommendedFuelOctane": 85,
      "HasSuperCharger": false,
      "NumberOfCylinders": 6,
      "HasTurbo": false,
      "FuelType": "Gas",
      "HorsePower": 330,
      "Torque": 360
    }
  }
]